pysparkify/__init__.py
pysparkify/lib/__init__.py
pysparkify/lib/app.py
pysparkify/lib/context_manager.py
pysparkify/lib/logger.py
pysparkify/lib/sink/__init__.py
pysparkify/lib/sink/csv_sink.py
pysparkify/lib/sink/postgres_sink.py
pysparkify/lib/sink/redshift_sink.py
pysparkify/lib/sink/s3_sink.py
pysparkify/lib/sink/sink.py
pysparkify/lib/sink/sink_factory.py
pysparkify/lib/source/__init__.py
pysparkify/lib/source/csv_source.py
pysparkify/lib/source/postgres_source.py
pysparkify/lib/source/redshift_source.py
pysparkify/lib/source/s3_source.py
pysparkify/lib/source/source.py
pysparkify/lib/source/source_factory.py
pysparkify/lib/transformer/__init__.py
pysparkify/lib/transformer/sql_transformer.py
pysparkify/lib/transformer/transformer.py
pysparkify/lib/transformer/transformer_factory.py
pysparkify/tests/__init__.py
pysparkify/tests/test_app.py
pysparkify-0.27.0.dist-info/METADATA
pysparkify-0.27.0.dist-info/WHEEL
pysparkify-0.27.0.dist-info/entry_points.txt
pysparkify-0.27.0.dist-info/top_level.txt
pysparkify-0.27.0.dist-info/RECORD
