Metadata-Version: 2.1
Name: pysparkify
Version: 0.27.0
Summary: Spark based ETL
Home-page: https://github.com/raohammad/pysparkify
Author: Hammad Aslam KHAN
Author-email: raohammad@gmail.com
License: MIT
Keywords: python,pysparkify,etl,bigdata
Classifier: Development Status :: 3 - Alpha
Classifier: Intended Audience :: Developers
Classifier: License :: OSI Approved :: MIT License
Classifier: Programming Language :: Python
Requires-Dist: pyspark >=3.0.0
Requires-Dist: pyyaml >=5.3
